satstream_python_sdk/__init__.py
satstream_python_sdk/api_client.py
satstream_python_sdk/configuration.py
satstream_python_sdk/rest.py
satstream_python_sdk/api/__init__.py
satstream_python_sdk/api/addresses_api.py
satstream_python_sdk/api/blocks_api.py
satstream_python_sdk/api/fees_api.py
satstream_python_sdk/api/inscriptions_api.py
satstream_python_sdk/api/mempool_api.py
satstream_python_sdk/api/mining_api.py
satstream_python_sdk/api/network_api.py
satstream_python_sdk/api/outputs_api.py
satstream_python_sdk/api/psbts_api.py
satstream_python_sdk/api/runes_api.py
satstream_python_sdk/api/satoshis_api.py
satstream_python_sdk/api/scripts_api.py
satstream_python_sdk/api/status_api.py
satstream_python_sdk/api/transactions_api.py
satstream_python_sdk/models/__init__.py
satstream_python_sdk/models/address_response.py
satstream_python_sdk/models/address_rune_delta.py
satstream_python_sdk/models/all_of_block_vin2_script_sig.py
satstream_python_sdk/models/all_of_block_vin3_prevout.py
satstream_python_sdk/models/all_of_decoded_psbt_input_final_scriptsig.py
satstream_python_sdk/models/all_of_decoded_psbt_input_non_witness_utxo.py
satstream_python_sdk/models/all_of_decoded_psbt_input_redeem_script.py
satstream_python_sdk/models/all_of_decoded_psbt_input_unknown.py
satstream_python_sdk/models/all_of_decoded_psbt_input_witness_script.py
satstream_python_sdk/models/all_of_decoded_psbt_input_witness_utxo.py
satstream_python_sdk/models/all_of_decoded_psbt_output_redeem_script.py
satstream_python_sdk/models/all_of_decoded_psbt_output_unknown.py
satstream_python_sdk/models/all_of_decoded_psbt_output_witness_script.py
satstream_python_sdk/models/all_of_decoded_psbt_unknown.py
satstream_python_sdk/models/all_of_decoded_psbttx.py
satstream_python_sdk/models/all_of_decoded_script_segwit.py
satstream_python_sdk/models/all_of_fee_horizon_estimate_fail.py
satstream_python_sdk/models/all_of_fee_horizon_estimate_pass.py
satstream_python_sdk/models/all_of_mempool_entry_fees.py
satstream_python_sdk-1.0.55.dist-info/METADATA
satstream_python_sdk-1.0.55.dist-info/WHEEL
satstream_python_sdk-1.0.55.dist-info/top_level.txt
satstream_python_sdk-1.0.55.dist-info/RECORD
